molotov_ext/__init__.py
molotov_ext/formatters.py
molotov_ext/record_table.py
molotov_ext/recorder.py
molotov_ext/records.py
molotov_ext/reporter.py
molotov_ext/scenario.py
molotov_ext-1.0.1.dist-info/LICENSE
molotov_ext-1.0.1.dist-info/METADATA
molotov_ext-1.0.1.dist-info/WHEEL
molotov_ext-1.0.1.dist-info/top_level.txt
molotov_ext-1.0.1.dist-info/RECORD
