Metadata-Version: 2.1
Name: molotov-ext
Version: 1.0.1
Summary: Library for collecting metrics for Molotov
Home-page: https://github.com/2gis-test-labs/molotov-ext
Author: 2GIS Test Labs
Author-email: test-labs@2gis.ru
License: Apache-2.0
Classifier: License :: OSI Approved :: Apache Software License
Classifier: Programming Language :: Python :: 3.7
Classifier: Programming Language :: Python :: 3.8
Classifier: Programming Language :: Python :: 3.9
Classifier: Programming Language :: Python :: 3.10
Requires-Python: >=3.7
License-File: LICENSE
Requires-Dist: aiohttp (<4,>=3.6)
Requires-Dist: molotov (<3,>=2.4)
